iterable_subprocess.py
iterable_subprocess-0.0.16.dist-info/METADATA
iterable_subprocess-0.0.16.dist-info/WHEEL
iterable_subprocess-0.0.16.dist-info/licenses/LICENSE
iterable_subprocess-0.0.16.dist-info/RECORD
