Metadata-Version: 2.1
Name: iterable-subprocess
Version: 0.0.16
Summary: Python context manager to communicate with a subprocess using iterables of bytes rather Python's built-in subprocess module
Project-URL: Source, https://github.com/uktrade/iterable-subprocess
Author-email: Department for International Trade <sre@digital.trade.gov.uk>
License-File: LICENSE
Classifier: License :: OSI Approved :: MIT License
Classifier: Programming Language :: Python :: 3
Requires-Python: >=3.6.7
Provides-Extra: dev
Requires-Dist: psutil; extra == 'dev'
Requires-Dist: pytest-cov; extra == 'dev'
